{
  "tasks": [
    "{\"id\":\"t-20260413-003338622\",\"title\":\"\",\"title_customized\":0,\"description\":null,\"status\":\"inbox\",\"body\":\"发布 mlt 和 zotero\",\"created_at\":1776040418622,\"updated_at\":1776040418633,\"completed_at\":null,\"ddl\":null,\"ddl_type\":null,\"planned_at\":null,\"role_id\":\"role-mn1o2z7q-1\",\"role_ids\":null,\"parent_id\":null,\"source_stream_id\":\"se-20260402-101021\",\"priority\":null,\"promoted\":null,\"phase\":\"understood\",\"kanban_column\":null,\"task_type\":null,\"tags\":\"[]\",\"subtask_ids\":\"[]\",\"resources\":\"[]\",\"reminders\":\"[]\",\"submissions\":\"[]\",\"postponements\":\"[]\",\"status_history\":\"[]\",\"progress_logs\":\"[]\",\"version\":0,\"deleted_at\":null}",
    "{\"id\":\"t-20260410-141208239\",\"title\":\"\",\"title_customized\":0,\"description\":null,\"status\":\"inbox\",\"body\":\"发布 mlt 和 zotero\",\"created_at\":1775830328239,\"updated_at\":1776018798447,\"completed_at\":null,\"ddl\":null,\"ddl_type\":null,\"planned_at\":null,\"role_id\":\"role-mn1o2z7q-1\",\"role_ids\":null,\"parent_id\":null,\"source_stream_id\":\"se-20260402-101021\",\"priority\":null,\"promoted\":null,\"phase\":\"understood\",\"kanban_column\":null,\"task_type\":null,\"tags\":\"[]\",\"subtask_ids\":\"[]\",\"resources\":\"[]\",\"reminders\":\"[]\",\"submissions\":\"[]\",\"postponements\":\"[]\",\"status_history\":\"[]\",\"progress_logs\":\"[]\",\"version\":0,\"deleted_at\":null}",
    "{\"id\":\"t-20260413-103214381\",\"title\":\"我应该要去干点活\",\"title_customized\":1,\"description\":null,\"status\":\"inbox\",\"body\":\"\",\"created_at\":1776076334381,\"updated_at\":1776076334396,\"completed_at\":null,\"ddl\":null,\"ddl_type\":null,\"planned_at\":null,\"role_id\":null,\"role_ids\":null,\"parent_id\":null,\"source_stream_id\":null,\"priority\":null,\"promoted\":null,\"phase\":\"understood\",\"kanban_column\":null,\"task_type\":null,\"tags\":\"[]\",\"subtask_ids\":\"[]\",\"resources\":\"[]\",\"reminders\":\"[]\",\"submissions\":\"[]\",\"postponements\":\"[]\",\"status_history\":\"[]\",\"progress_logs\":\"[]\",\"version\":0,\"deleted_at\":null}",
    "{\"id\":\"t-20260324-115600308\",\"title\":\"\",\"title_customized\":0,\"description\":null,\"status\":\"completed\",\"body\":\"我还在更新我的个人 todo 项目\",\"created_at\":1774353360308,\"updated_at\":1775830340000,\"completed_at\":1775830450533,\"ddl\":null,\"ddl_type\":null,\"planned_at\":null,\"role_id\":\"role-mn4az287-1\",\"role_ids\":null,\"parent_id\":null,\"source_stream_id\":\"se-20260324-194332\",\"priority\":null,\"promoted\":null,\"phase\":null,\"kanban_column\":null,\"task_type\":null,\"tags\":\"[]\",\"subtask_ids\":\"[\\\"t-20260324-115638915\\\"]\",\"resources\":\"[]\",\"reminders\":\"[]\",\"submissions\":\"[]\",\"postponements\":\"[]\",\"status_history\":\"[]\",\"progress_logs\":\"[]\",\"version\":0,\"deleted_at\":null}",
    "{\"id\":\"t-20260324-115638915\",\"title\":\"\",\"title_customized\":0,\"description\":null,\"status\":\"inbox\",\"body\":\"\",\"created_at\":1774353518915,\"updated_at\":1774353518915,\"completed_at\":null,\"ddl\":null,\"ddl_type\":null,\"planned_at\":null,\"role_id\":null,\"role_ids\":null,\"parent_id\":\"t-20260324-115600308\",\"source_stream_id\":null,\"priority\":null,\"promoted\":null,\"phase\":null,\"kanban_column\":null,\"task_type\":null,\"tags\":\"[]\",\"subtask_ids\":\"[]\",\"resources\":\"[]\",\"reminders\":\"[]\",\"submissions\":\"[]\",\"postponements\":\"[]\",\"status_history\":\"[]\",\"progress_logs\":\"[]\",\"version\":0,\"deleted_at\":null}"
  ],
  "stream_entries": [
    "{\"id\":\"se-20260402-101021\",\"content\":\"发布 mlt 和 zotero\",\"entry_type\":\"task\",\"timestamp\":1775095821000,\"date_key\":\"2026-04-02\",\"role_id\":\"role-mn1o2z7q-1\",\"extracted_task_id\":\"t-20260413-003338622\",\"tags\":\"[]\",\"attachments\":\"[]\",\"version\":0,\"deleted_at\":null,\"updated_at\":1776076611359}",
    "{\"id\":\"se-20260324-194332\",\"content\":\"我还在更新我的个人 todo 项目\",\"entry_type\":\"spark\",\"timestamp\":1774352612000,\"date_key\":\"2026-03-24\",\"role_id\":\"role-mn4az287-1\",\"extracted_task_id\":\"t-20260324-115600308\",\"tags\":\"[]\",\"attachments\":\"[]\",\"version\":0,\"deleted_at\":null,\"updated_at\":1776076611359}"
  ]
}
